analyzer/__init__.py
analyzer/token_analysis.py
token_analyzer-0.1.2.dist-info/LICENSE
token_analyzer-0.1.2.dist-info/METADATA
token_analyzer-0.1.2.dist-info/WHEEL
token_analyzer-0.1.2.dist-info/top_level.txt
token_analyzer-0.1.2.dist-info/RECORD
