Metadata-Version: 2.1
Name: token-analyzer
Version: 0.1.2
Summary: A Python library for analyzing and calculating token usage costs for various LLM models like OpenAI and Anthropic, with support for real-time currency conversion.
Home-page: https://github.com/krtarunsingh/token_analyzer
Author: Tarun Kr. Singh
Author-email: krtarunsingh@gmail.com
Classifier: Programming Language :: Python :: 3
Classifier: License :: OSI Approved :: MIT License
Classifier: Operating System :: OS Independent
Requires-Python: >=3.6
License-File: LICENSE
Requires-Dist: freecurrencyapi
Requires-Dist: logging
